{
  "id": "powdered_silver",
  "name": "Powdered Silver",
  "description": "Finely ground silver with purifying properties. Used in protective wards and sanctification rituals.",
  "category": "material",
  "subtype": "magical_component",
  "flags": {
    "equippable": false,
    "consumable": false,
    "craftable": false,
    "magical": true,
    "tool": false,
    "crafting_material": true
  },
  "weight": 0.1,
  "value": 25,
  "max_stack": 20,
  "ascii_char": ".",
  "ascii_color": "#CCCCFF"
}
